getr/__init__.py
getr/_modidx.py
getr/attr.py
getr/atyp.py
getr/cons.py
getr/core.py
getr/grds.py
getr-0.0.10.dist-info/LICENSE
getr-0.0.10.dist-info/METADATA
getr-0.0.10.dist-info/WHEEL
getr-0.0.10.dist-info/entry_points.txt
getr-0.0.10.dist-info/top_level.txt
getr-0.0.10.dist-info/RECORD
