Metadata-Version: 2.1
Name: getr
Version: 0.0.10
Summary: getr
Home-page: https://github.com/dsm-72/getr
Author: dsm-72
Author-email: sumner.magruder@yale.edu
License: Apache Software License 2.0
Keywords: getr is question bool type guard typeguard check getr
Classifier: Development Status :: 4 - Beta
Classifier: Intended Audience :: Developers
Classifier: Natural Language :: English
Classifier: Programming Language :: Python :: 3.11
Classifier: License :: OSI Approved :: Apache Software License
Requires-Python: >=3.11
License-File: LICENSE
Requires-Dist: ptyp
Requires-Dist: atyp
Requires-Dist: itry
Requires-Dist: nchr
Requires-Dist: nlit
Requires-Dist: chck
Requires-Dist: hasr
Provides-Extra: dev
